tiny_lfm.py
tiny_lfm_builtin\__init__.py
tiny_lfm_builtin\tiny_lfm_builtin.pyd
tiny_lfm_builtin-0.0.3.dist-info\METADATA
tiny_lfm_builtin-0.0.3.dist-info\WHEEL
tiny_lfm_builtin-0.0.3.dist-info\RECORD
