Metadata-Version: 2.4
Name: tiny_lfm_builtin
Version: 0.0.3
Classifier: Programming Language :: Rust
Classifier: Programming Language :: Python :: Implementation :: CPython
Classifier: Programming Language :: Python :: Implementation :: PyPy
Classifier: Programming Language :: Python :: 3
Classifier: License :: OSI Approved :: MIT License
Classifier: Operating System :: POSIX :: Linux
Classifier: Operating System :: Microsoft :: Windows
Classifier: Operating System :: MacOS
Summary: LiquidAI-LFM2-350M rust inference engine embedded in a python package
Author-email: Carlo Moro <cnmoro@gmail.com>
Requires-Python: >=3.8
Project-URL: Repository, https://github.com/cnmoro/tiny-lfm-builtin
